nyxcrypta/__init__.py
nyxcrypta/main.py
nyxcrypta/test_runner.py
nyxcrypta/cli/__init__.py
nyxcrypta/cli/commands.py
nyxcrypta/cli/interactive.py
nyxcrypta/cli/parser.py
nyxcrypta/core/__init__.py
nyxcrypta/core/compatibility.py
nyxcrypta/core/crypto.py
nyxcrypta/core/security.py
nyxcrypta/core/utils.py
nyxcrypta-1.5.0.dist-info/LICENSE
nyxcrypta-1.5.0.dist-info/METADATA
nyxcrypta-1.5.0.dist-info/WHEEL
nyxcrypta-1.5.0.dist-info/entry_points.txt
nyxcrypta-1.5.0.dist-info/top_level.txt
nyxcrypta-1.5.0.dist-info/RECORD
