Metadata-Version: 2.1
Name: nyxcrypta
Version: 1.5.0
Summary: Cryptography tool based on RSA and AES
Home-page: https://github.com/Division-of-Cyber-Anarchy/NyxCrypta
Author: DCA (Malic1tus, Calypt0sis, ViraL0x, NyxCrypta)
Author-email: malic1tus@proton.me
Classifier: Programming Language :: Python :: 3
Classifier: License :: OSI Approved :: MIT License
Classifier: Operating System :: OS Independent
Requires-Python: >=3.8
License-File: LICENSE
Requires-Dist: cryptography>=41.0.5
Requires-Dist: argon2-cffi>=20.1.0
Requires-Dist: cffi>=1.17.1
Requires-Dist: tqdm>=4.67
Requires-Dist: questionary>=2.0.1
Requires-Dist: rich>=13.7.0
